libscraper/__init__.py
libscraper-0.0.6.dist-info/METADATA
libscraper-0.0.6.dist-info/WHEEL
libscraper-0.0.6.dist-info/top_level.txt
libscraper-0.0.6.dist-info/RECORD
