Metadata-Version: 2.1
Name: libscraper
Version: 0.0.6
Summary: kekw
Author: Jonas
Author-email: kekw@kekw.kekw
Keywords: python
Classifier: Operating System :: Microsoft :: Windows
